MANIFEST.in
README.rst
requirements.txt
setup.py
logicbook/__init__.py
logicbook.egg-info/PKG-INFO
logicbook.egg-info/SOURCES.txt
logicbook.egg-info/dependency_links.txt
logicbook.egg-info/entry_points.txt
logicbook.egg-info/requires.txt
logicbook.egg-info/top_level.txt
logicbook/cli/__init__.py
logicbook/cli/initializer.py
logicbook/cli/root.py
logicbook/cli/runner.py
logicbook/cli/utils.py
logicbook/core/server.py
logicbook/template/.logicbook/config.yaml
logicbook/template/logics/calculator/calculator.py
logicbook/template/logics/calculator/calculator_add.md
logicbook/template/logics/calculator/calculator_book.py
logicbook/template/logics/calculator/calculator_sub.md
logicbook/template/logics/calculator/test_calculator.py
logicbook/template/logics/calculator/__pycache__/calculator.cpython-39.pyc
logicbook/template/logics/calculator/__pycache__/calculator_book.cpython-39.pyc
logicbook/template/logics/calculator/__pycache__/test_calculator.cpython-39.pyc
logicbook/template/logics/join/join.md
logicbook/template/logics/join/join.py
logicbook/template/logics/join/join_book.py
logicbook/template/logics/join/test_join.py
logicbook/template/logics/join/__pycache__/join.cpython-39.pyc
logicbook/template/logics/join/__pycache__/join_book.cpython-39.pyc
logicbook/template/logics/join/__pycache__/test_join.cpython-39.pyc
logicbook/ui/build/asset-manifest.json
logicbook/ui/build/favicon.ico
logicbook/ui/build/index.html
logicbook/ui/build/logo192.png
logicbook/ui/build/logo512.png
logicbook/ui/build/manifest.json
logicbook/ui/build/robots.txt