Metadata-Version: 1.0
Name: logicbook
Version: 0.2.0
Summary: Logicbook is an open source tool for building python logics in isolation. It streamlines logic development, testing, and documentation.
Home-page: https://ruihirano.github.io/logicbook/
Author: Rui Hirano
Author-email: UNKNOWN
License: MIT
Platform: UNKNOWN
